84ecd45f856bb86c89cd__mypyc.cp312-win_amd64.pyd
cutesy/__init__.py
cutesy/__main__.py
cutesy/cli.cp312-win_amd64.pyd
cutesy/cli.py
cutesy/linter.cp312-win_amd64.pyd
cutesy/linter.py
cutesy/rules.py
cutesy/types.py
cutesy/attribute_processors/__init__.cp312-win_amd64.pyd
cutesy/attribute_processors/__init__.py
cutesy/attribute_processors/constants.cp312-win_amd64.pyd
cutesy/attribute_processors/constants.py
cutesy/attribute_processors/reindent.cp312-win_amd64.pyd
cutesy/attribute_processors/reindent.py
cutesy/attribute_processors/types.cp312-win_amd64.pyd
cutesy/attribute_processors/types.py
cutesy/attribute_processors/whitespace.cp312-win_amd64.pyd
cutesy/attribute_processors/whitespace.py
cutesy/attribute_processors/class_ordering/__init__.cp312-win_amd64.pyd
cutesy/attribute_processors/class_ordering/__init__.py
cutesy/attribute_processors/class_ordering/tailwind.cp312-win_amd64.pyd
cutesy/attribute_processors/class_ordering/tailwind.py
cutesy/attribute_processors/class_ordering/types.cp312-win_amd64.pyd
cutesy/attribute_processors/class_ordering/types.py
cutesy/preprocessors/__init__.cp312-win_amd64.pyd
cutesy/preprocessors/__init__.py
cutesy/preprocessors/django.cp312-win_amd64.pyd
cutesy/preprocessors/django.py
cutesy/preprocessors/types.cp312-win_amd64.pyd
cutesy/preprocessors/types.py
cutesy/utilities/__init__.cp312-win_amd64.pyd
cutesy/utilities/__init__.py
cutesy/utilities/collections.cp312-win_amd64.pyd
cutesy/utilities/collections.py
cutesy-1.0b20.dist-info/licenses/LICENSE
tests/__init__.py
tests/integration/__init__.py
tests/integration/test_cutesy.py
tests/integration/test_tailwind.py
tests/private/__init__.py
tests/private/test_class_ordering.py
tests/private/test_linter.py
tests/unit/__init__.py
tests/unit/test_blank_line_removal.py
tests/unit/test_class_ordering.py
tests/unit/test_class_ordering_types.py
tests/unit/test_cli.py
tests/unit/test_collections.py
tests/unit/test_linter.py
tests/unit/test_main.py
tests/unit/test_preprocessor.py
tests/unit/test_preprocessor_django.py
cutesy-1.0b20.dist-info/METADATA
cutesy-1.0b20.dist-info/WHEEL
cutesy-1.0b20.dist-info/entry_points.txt
cutesy-1.0b20.dist-info/top_level.txt
cutesy-1.0b20.dist-info/RECORD
