Metadata-Version: 2.4
Name: cutesy
Version: 1.0b20
Summary: A linter & formatter for consistent HTML code, or else.
Home-page: https://github.com/chasefinch/cutesy
Author: Chase Finch
Author-email: chase@finch.email
Keywords: Cutesy,HTML,lint,linter,format,formatter,autoformat,autoformatter
Classifier: Programming Language :: Python :: 3
Classifier: Programming Language :: Python :: 3.11
Classifier: Programming Language :: Python :: 3.12
Classifier: Programming Language :: Python :: 3.13
Classifier: Programming Language :: Rust
Classifier: License :: OSI Approved :: Apache Software License
Classifier: Operating System :: OS Independent
Requires-Python: >=3.11
License-File: LICENSE
Requires-Dist: data-enum<3,>=2.0.1
Requires-Dist: click<9,>=8.1.8
Dynamic: author
Dynamic: author-email
Dynamic: classifier
Dynamic: description
Dynamic: description-content-type
Dynamic: home-page
Dynamic: keywords
Dynamic: license-file
Dynamic: requires-dist
Dynamic: requires-python
Dynamic: summary
